[
  {
    "identificadorPreso": "1",
    "nombre": "Victor",
    "apellido": "Marlor",
    "sexo": "H",
    "fechaNacimiento": {
      "year": 2003,
      "month": 5,
      "day": 20
    },
    "edad": 68,
    "delito": "Daños",
    "fechaSalida": {
      "year": 2025,
      "month": 5,
      "day": 22
    }
  },
  {
    "identificadorPreso": "72iL3IChkrDkIvZ",
    "nombre": "Nico",
    "apellido": "Salmeron",
    "sexo": "H",
    "fechaNacimiento": {
      "year": 1954,
      "month": 5,
      "day": 20
    },
    "edad": 68,
    "delito": "Usurpacion",
    "fechaSalida": {
      "year": 2028,
      "month": 5,
      "day": 25
    }
  },
  {
    "identificadorPreso": "VRU97gMhHWgeIff",
    "nombre": "Hector",
    "apellido": "Valdes",
    "sexo": "H",
    "fechaNacimiento": {
      "year": 1932,
      "month": 7,
      "day": 7
    },
    "edad": 90,
    "delito": "Daños",
    "fechaSalida": {
      "year": 2025,
      "month": 2,
      "day": 25
    }
  },
  {
    "identificadorPreso": "fBqBmEvcI45LjRa",
    "nombre": "Seve",
    "apellido": "Goicoechea",
    "sexo": "H",
    "fechaNacimiento": {
      "year": 1912,
      "month": 2,
      "day": 28
    },
    "edad": 105,
    "delito": "Falsedades documentales",
    "fechaSalida": {
      "year": 2024,
      "month": 7,
      "day": 14
    }
  },
  {
    "identificadorPreso": "vqBKQmueYoqVNGU",
    "nombre": "Ricardo",
    "apellido": "Enriquez",
    "sexo": "H",
    "fechaNacimiento": {
      "year": 1917,
      "month": 7,
      "day": 7
    },
    "edad": 90,
    "delito": "Daños",
    "fechaSalida": {
      "year": 2025,
      "month": 2,
      "day": 25
    }
  },
  {
    "identificadorPreso": "zyVTb3hOMmYDDQp",
    "nombre": "Guadalupe",
    "apellido": "Garcia",
    "sexo": "F",
    "fechaNacimiento": {
      "year": 1997,
      "month": 9,
      "day": 21
    },
    "edad": 25,
    "delito": "Robos",
    "fechaSalida": {
      "year": 2024,
      "month": 4,
      "day": 22
    }
  },
  {
    "identificadorPreso": "P9qI45K7QSuhKZk",
    "nombre": "Florencia",
    "apellido": "Palau",
    "sexo": "F",
    "fechaNacimiento": {
      "year": 1997,
      "month": 11,
      "day": 12
    },
    "edad": 90,
    "delito": "Daños",
    "fechaSalida": {
      "year": 2028,
      "month": 11,
      "day": 25
    }
  },
  {
    "identificadorPreso": "q66r8f0npQvby8T",
    "nombre": "Kike",
    "apellido": "Caro",
    "sexo": "H",
    "fechaNacimiento": {
      "year": 1920,
      "month": 2,
      "day": 10
    },
    "edad": 102,
    "delito": "Usurpacion",
    "fechaSalida": {
      "year": 2030,
      "month": 5,
      "day": 29
    }
  },
  {
    "identificadorPreso": "HVHxV8L8nZxskjh",
    "nombre": "Vidal",
    "apellido": "Bardia",
    "sexo": "H",
    "fechaNacimiento": {
      "year": 1947,
      "month": 1,
      "day": 11
    },
    "edad": 75,
    "delito": "Daños a la propiedad privada",
    "fechaSalida": {
      "year": 2025,
      "month": 1,
      "day": 3
    }
  }
]